baseball_stats_mcp/__init__.py
baseball_stats_mcp/demo_visualizations.py
baseball_stats_mcp/run_server.py
baseball_stats_mcp/server.py
baseball_stats_mcp-1.0.1.dist-info/licenses/LICENSE
baseball_stats_mcp-1.0.1.dist-info/METADATA
baseball_stats_mcp-1.0.1.dist-info/WHEEL
baseball_stats_mcp-1.0.1.dist-info/entry_points.txt
baseball_stats_mcp-1.0.1.dist-info/top_level.txt
baseball_stats_mcp-1.0.1.dist-info/RECORD
