Metadata-Version: 2.4
Name: baseball-stats-mcp
Version: 1.0.1
Summary: The most comprehensive baseball analytics MCP server with 32 advanced tools
Home-page: https://github.com/aringadre76/baseball-stats-mcp
Author: Arin Gadre
Author-email: Arin Gadre <aringadre76@gmail.com>
Maintainer-email: Arin Gadre <aringadre76@gmail.com>
License: MIT License
Project-URL: Homepage, https://github.com/aringadre76/baseball-stats-mcp
Project-URL: Repository, https://github.com/aringadre76/baseball-stats-mcp
Project-URL: Source, https://github.com/aringadre76/baseball-stats-mcp
Project-URL: Bug Reports, https://github.com/aringadre76/baseball-stats-mcp/issues
Project-URL: Documentation, https://github.com/aringadre76/baseball-stats-mcp/blob/main/docs/
Project-URL: Issues, https://github.com/aringadre76/baseball-stats-mcp/issues
Keywords: baseball,mcp,analytics,statcast,sabermetrics,mlb,sports,statistics
Classifier: Development Status :: 4 - Beta
Classifier: Intended Audience :: Developers
Classifier: Intended Audience :: Science/Research
Classifier: Topic :: Scientific/Engineering :: Information Analysis
Classifier: Topic :: Software Development :: Libraries :: Python Modules
Classifier: License :: OSI Approved :: MIT License
Classifier: Programming Language :: Python :: 3
Classifier: Programming Language :: Python :: 3.8
Classifier: Programming Language :: Python :: 3.9
Classifier: Programming Language :: Python :: 3.10
Classifier: Programming Language :: Python :: 3.11
Classifier: Programming Language :: Python :: 3.12
Classifier: Operating System :: OS Independent
Requires-Python: >=3.8
License-File: LICENSE
Requires-Dist: mcp>=1.0.0
Requires-Dist: requests>=2.31.0
Requires-Dist: pandas>=2.0.0
Requires-Dist: matplotlib>=3.7.0
Requires-Dist: seaborn>=0.12.0
Requires-Dist: plotly>=5.15.0
Requires-Dist: numpy>=1.24.0
Requires-Dist: python-dotenv>=1.0.0
Requires-Dist: firecrawl>=0.1.0
Dynamic: author
Dynamic: home-page
Dynamic: license-file
Dynamic: requires-python
